uniport/__init__.py
uniport/data_loader.py
uniport/function.py
uniport/logger.py
uniport/metrics.py
uniport/model/__init__.py
uniport/model/layer.py
uniport/model/loss.py
uniport/model/utils.py
uniport/model/vae.py
uniport-1.3.dist-info/METADATA
uniport-1.3.dist-info/WHEEL
uniport-1.3.dist-info/top_level.txt
uniport-1.3.dist-info/RECORD
