Metadata-Version: 2.1
Name: uniport
Version: 1.3
Summary: a unified computational framework for single-cell data integration with optimal transport
Home-page: https://github.com/caokai1073/uniPort
Author: caokai
Author-email: caokai1073@gmail.com
License: MIT Licence
Platform: any
Requires-Python: >3.8.0
Requires-Dist: numpy (>=1.17.2)
Requires-Dist: pandas (>=0.25.1)
Requires-Dist: scipy (>=1.3.1)
Requires-Dist: scikit-learn (>=0.22.1)
Requires-Dist: torch (>=1.0.0)
Requires-Dist: scanpy (>=1.4.5)
Requires-Dist: tqdm (>=4.28.1)
Requires-Dist: matplotlib (>=3.0.3)
Requires-Dist: leidenalg (>=0.8.3)
